[
    {
        "function": "minecraft:set_lore",
        "entity": "this",
        "lore": [
            [
                {
                    "text": "feather_falling ",
                    "color": "gray"
                },
                {
                    "nbt": "details.level",
                    "storage": "minecraft:ench",
                    "color": "gray"
                },
                {
                    "text": "/IV",
                    "color": "gray"
                },
                {
                    "text": "[Boots]",
                    "color": "dark_gray"
                }
            ],
            {
                "text": "Reduces fall damage taken",
                "color": "light_purple"
            }
        ],
        "mode": "insert"
    }
]